dbstep/Dbstep.py
dbstep/__init__.py
dbstep/__main__.py
dbstep/calculator.py
dbstep/constants.py
dbstep/graph.py
dbstep/mcgowan.csv
dbstep/parse_data.py
dbstep/sterics.py
dbstep/writer.py
dbstep/examples/1Nap.xyz
dbstep/examples/1Nap_steric.py
dbstep/examples/1Nap_transform.xyz
dbstep/examples/35diMePh.xyz
dbstep/examples/4ClPh.xyz
dbstep/examples/4MeOPh.xyz
dbstep/examples/4MePh.xyz
dbstep/examples/Ad.xyz
dbstep/examples/Ad_steric.py
dbstep/examples/Ad_transform.xyz
dbstep/examples/Benchmark.csv
dbstep/examples/Bn.xyz
dbstep/examples/CEt3.xyz
dbstep/examples/CH2iPr.xyz
dbstep/examples/CH2tBu.xyz
dbstep/examples/CHEt2.xyz
dbstep/examples/CHPr2.xyz
dbstep/examples/CHiPr2.xyz
dbstep/examples/DBLOOP
dbstep/examples/Et.xyz
dbstep/examples/H.xyz
dbstep/examples/Me.xyz
dbstep/examples/Ph.xyz
dbstep/examples/Untitled.ipynb
dbstep/examples/cHex.xyz
dbstep/examples/iPr.xyz
dbstep/examples/nBu.xyz
dbstep/examples/nPr.xyz
dbstep/examples/smiles.txt
dbstep/examples/tBu.xyz
dbstep/examples/.ipynb_checkpoints/Untitled-checkpoint.ipynb
dbstep-1.1.0.dist-info/LICENSE.txt
dbstep-1.1.0.dist-info/METADATA
dbstep-1.1.0.dist-info/WHEEL
dbstep-1.1.0.dist-info/top_level.txt
dbstep-1.1.0.dist-info/RECORD
