Metadata-Version: 2.1
Name: dbstep
Version: 1.1.0
Summary: DFT Based Steric Parameters
Home-page: https://github.com/bobbypaton/DBSTEP
Download-URL: https://github.com/patonlab/DBSTEP/archive/refs/tags/1.1.0.zip
Author: Guilian Luchini, Toby Patterson, Robert Paton
Author-email: patonlab@colostate.edu
License: MIT
Keywords: compchem,steric,sterimol,informatics
Platform: UNKNOWN
Classifier: License :: OSI Approved :: MIT License
Requires-Python: >=3.6
License-File: LICENSE.txt
Requires-Dist: numpy
Requires-Dist: numba
Requires-Dist: scipy
Requires-Dist: cclib
